motrainer/__init__.py
motrainer/dnn.py
motrainer/jackknife.py
motrainer/model.py
motrainer/splitter.py
motrainer/util.py
motrainer-0.1.7.dist-info/LICENSE
motrainer-0.1.7.dist-info/METADATA
motrainer-0.1.7.dist-info/WHEEL
motrainer-0.1.7.dist-info/top_level.txt
motrainer-0.1.7.dist-info/RECORD
