Metadata-Version: 2.1
Name: motrainer
Version: 0.1.7
Summary: Parallel Training Measurement Operators (MO) for Data Assimilation (DA) Applications
Author: Fakhereh Sarah Alidoost, Pranav Chandramouli, Francesco Nattino, Meiert Willem Grootes, Xu Shan, Sonja Georgievska, Susan Steele-Dunne
Author-email: Ou Ku <o.ku@esciencecenter.nl>
License: 
Project-URL: repository, https://github.com/VegeWaterDynamics/motrainer
Project-URL: doi, https://zenodo.org/doi/10.5281/zenodo.7540442
Project-URL: documentation, https://VegeWaterDynamics.github.io/motrainer/
Project-URL: changelog, https://VegeWaterDynamics.github.io/motrainer/CHANGELOG/
Keywords: machine learning,earth observation,data assimilations,training,sensor
Classifier: Development Status :: 3 - Alpha
Classifier: Intended Audience :: Developers
Classifier: License :: OSI Approved :: Apache Software License
Classifier: Natural Language :: English
Classifier: Programming Language :: Python :: 3.10
Classifier: Programming Language :: Python :: 3.11
Requires-Python: >=3.10
License-File: LICENSE
Requires-Dist: dask[complete]
Requires-Dist: ipykernel
Requires-Dist: numpy
Requires-Dist: pandas
Requires-Dist: scikit-learn <=1.4.2
Requires-Dist: scikit-optimize
Requires-Dist: scipy
Requires-Dist: tensorflow
Requires-Dist: xarray
Requires-Dist: zarr
Provides-Extra: demo
Requires-Dist: jupyterlab ; extra == 'demo'
Requires-Dist: matplotlib ; extra == 'demo'
Requires-Dist: dask-ml ; extra == 'demo'
Requires-Dist: dask-labextension ; extra == 'demo'
Provides-Extra: dev
Requires-Dist: pytest ; extra == 'dev'
Requires-Dist: pytest-cov ; extra == 'dev'
Requires-Dist: pycodestyle ; extra == 'dev'
Requires-Dist: ruff ; extra == 'dev'
Provides-Extra: docs
Requires-Dist: mkdocs ; extra == 'docs'
Requires-Dist: mkdocs-material ; extra == 'docs'
Requires-Dist: mkdocs-jupyter ; extra == 'docs'
Requires-Dist: mkdocstrings[python] ; extra == 'docs'
Requires-Dist: mkdocs-gen-files ; extra == 'docs'
